{
  "date": "2025년 09월 14일, 일요일 오후 14시 00분",
  "location": "포스코센터, 서관 4층 아트홀",
  "gretting": "서로 마주 보며 다져온 사랑을\n이제 함께 한곳을 바라보며 걸어갈 수 있는\n큰 사랑으로 키우고자 합니다.\n저희 두 사람이 사랑의 이름으로 지켜나갈 수 있게\n앞날을 축복해 주시면 감사하겠습니다.",
  "groom": {
    "name": "황의민",
    "account_number": "국민은행 709402-00-260040",
    "parents": {
      "mother": {
        "name": "권현미",
        "account_number": "국민은행 511-21-0174-618"
      },
      "father": {
        "name": "황용배",
        "account_number": "국민은행 753501-01-274075"
      }
    }
  },
  "bride": {
    "name": "원유경",
    "account_number": "신한은행 110-501-283163",
    "parents": {
      "mother": {
        "name": "박미화",
        "account_number": "국민은행 001-01-2092-858"
      },
      "father": {
        "name": "원재연",
        "account_number": "○○은행 ***-***-******"
      }
    }
  },
  "kakaotalk": {
    "api_token": "",
    "wedding_invitation_url": "",
    "share_image": ""
  }
}
